basest/__init__.py
basest/exceptions.py
basest/core/__init__.py
basest/core/best_ratio.py
basest/core/decode.py
basest/core/encode.py
basest/core/utils.py
basest/encoders/__init__.py
basest/encoders/encoder.py
tests/core/__init__.py
tests/core/test_best_ratio.py
tests/core/test_encode_decode.py
tests/core/test_encode_decode_raw.py
tests/encoders/__init__.py
tests/encoders/test_encoder.py
basest-0.7.3.dist-info/LICENSE
basest-0.7.3.dist-info/METADATA
basest-0.7.3.dist-info/WHEEL
basest-0.7.3.dist-info/top_level.txt
basest-0.7.3.dist-info/RECORD
